RTFMaker/__init__.py
RTFMaker/core.py
RTFMaker/htmlconv.py
RTFMaker/utils.py
RTFMaker-0.1.9.dist-info/DESCRIPTION.rst
RTFMaker-0.1.9.dist-info/METADATA
RTFMaker-0.1.9.dist-info/RECORD
RTFMaker-0.1.9.dist-info/WHEEL
RTFMaker-0.1.9.dist-info/metadata.json
RTFMaker-0.1.9.dist-info/top_level.txt
